filabase/__init__.py
filabase/keyvaluestore.py
filabase/storage.py
filabase-0.1.0.dist-info/LICENSE
filabase-0.1.0.dist-info/METADATA
filabase-0.1.0.dist-info/WHEEL
filabase-0.1.0.dist-info/top_level.txt
filabase-0.1.0.dist-info/RECORD
