Metadata-Version: 2.1
Name: filabase
Version: 0.1.0
Summary: A small package that provides utilities for using files as     different types of databases
Home-page: https://bitbucket.org/geneshki/filabase
Author: Nikola Geneshki
Author-email: ngeneshki@gmail.com
License: UNKNOWN
Platform: UNKNOWN
Classifier: Programming Language :: Python :: 3
Classifier: License :: OSI Approved :: MIT License
Classifier: Operating System :: OS Independent
Requires-Python: >=3.9
License-File: LICENSE
